{"cameraMode":{"drawMode":0,"name":"Shaded","section":"Shading Mode"},"sceneLighting":true,"audioPlay":false,"sceneViewState":{"m_AlwaysRefresh":false,"showFog":true,"showSkybox":true,"showFlares":true,"showImageEffects":true,"showParticleSystems":true,"showVisualEffectGraphs":true,"m_FxEnabled":true},"in2DMode":false,"pivot":{"x":5.53759765625,"y":1.3563299179077149,"z":4.548511028289795},"rotation":{"x":-0.1350587159395218,"y":0.5635194778442383,"z":-0.09401265531778336,"w":-0.8095496296882629},"size":6.680518627166748,"orthographic":false}